{"sections":{"main":{"type":"main-page","disabled":true,"settings":{}},"rich-text":{"type":"rich-text","blocks":{"heading":{"type":"heading","settings":{"title":"Get in touch","heading-color":"#ec5459"}},"text":{"type":"text","settings":{"enlarge_text":false,"text":"<p>If you have any questions, want to work together on something amazing, or simply want to share your love for gifts, feel free to reach out to us. If there's one thing we love apart from making awesome gifts, it is talking!<\/p>"}}},"block_order":["heading","text"],"settings":{"align_text":"left","narrow_column":false,"color_scheme":"none","divider":false,"max-width":35}},"form":{"type":"contact-form","settings":{"title":"","text":"","show_phone":true,"narrow_column":true,"color_scheme":"1"}},"dd7394dd-210b-4c81-8dc6-035927bb3e48":{"type":"rich-text","blocks":{"876f0346-9333-4de4-a29f-ccf5b1d64613":{"type":"heading","settings":{"title":"For customer queries","heading-color":"#ec5459"}},"52e11f64-0450-4e18-a58a-a918357718ac":{"type":"icon-text","settings":{"image":"shopify:\/\/shop_images\/icons-01_1.svg","icon_text":"<p><a href=\"mailto:surprises@oyehappy.com\" title=\"mailto:surprises@oyehappy.com\">surprises@oyehappy.com<\/a><\/p>"}},"eadd4030-21a6-4b19-8328-2b210e1b6c15":{"type":"icon-text","settings":{"image":"shopify:\/\/shop_images\/icons-02_1.svg","icon_text":"<p><a href=\"tel:+919966687654\" title=\"tel:+919966687654\">+919966687654<\/a><\/p>"}},"63f82d7c-67e4-4837-a6bf-e49bbbfa051d":{"type":"heading","settings":{"title":"For corporate orders","heading-color":"#ec5459"}},"dd98a2cf-e909-470f-94f6-c73c954feb21":{"type":"icon-text","settings":{"image":"shopify:\/\/shop_images\/icons-01_1.svg","icon_text":"<p><a href=\"mailto:kunal@oyehappy.com\" title=\"mailto:kunal@oyehappy.com\">kunal@oyehappy.com<\/a><\/p>"}},"f0213334-4598-4755-912b-3f089fe1d24c":{"type":"icon-text","disabled":true,"settings":{"image":"shopify:\/\/shop_images\/icons-02_1.svg","icon_text":"<p><a href=\"tel:+918919886834\" title=\"tel:+918919886834\">+918919886834<\/a><\/p>"}}},"block_order":["876f0346-9333-4de4-a29f-ccf5b1d64613","52e11f64-0450-4e18-a58a-a918357718ac","eadd4030-21a6-4b19-8328-2b210e1b6c15","63f82d7c-67e4-4837-a6bf-e49bbbfa051d","dd98a2cf-e909-470f-94f6-c73c954feb21","f0213334-4598-4755-912b-3f089fe1d24c"],"settings":{"align_text":"left","narrow_column":false,"color_scheme":"1","divider":false,"max-width":35}}},"order":["main","rich-text","form","dd7394dd-210b-4c81-8dc6-035927bb3e48"]}